{
  "plugin": "poot-infinite-expanse",
  "repository": "https://github.com/Eggapegawsus/Eggapegawsus-endless-sky-plugins",
  "ships": [],
  "variants": [],
  "outfits": [
    {
      "name": "Infentessimal Outfit Expansion",
      "category": "Void Technology",
      "cost": 200000,
      "thumbnail": "outfit/vanillaplus/infentessimal-outfit",
      "mass": 0,
      "outfit space": 20,
      "unplunderable": 1,
      "description": "An infinitely small, yet unendingly deep storage device. whenever you look inside of this strange device, its internal storage compartment morphs to mach the outfit attatchment points of your ship.",
      "governments": {
        "Lemurias Extra ES Stuff/Lemurias-Extra-ES-Stuff": {
          "Sayari Plushie": true,
          "Anime Organization": true,
          "Republic": true
        },
        "Mega Freight/Mega-Freight": {
          "Republic": true
        },
        "sensor/sensor": {
          "sensor": true
        },
        "POOT/poot-senza-solaria": {
          "Syndicate": true
        },
        "POOT/endless_sky_senza_solaria": {
          "Syndicate": true
        },
        "POOT/poot-senza-solaria_senza_solaria": {
          "Syndicate": true
        }
      },
      "locations": {
        "official-game/endless-sky": {
          "Planets": [
            "Alfheim",
            "Bivrost",
            "Bloodsea",
            "Clark",
            "Crossroads",
            "Dancer",
            "Delve",
            "Freedom",
            "Furnace",
            "Gagarin",
            "Geyser",
            "Greenwater",
            "Haven",
            "Haze",
            "Heartland",
            "Ingot",
            "Jakobsen",
            "Longjump",
            "Mainsail",
            "Maker",
            "Millrace",
            "Mordente-Bridi",
            "New Argentina",
            "New Boston",
            "New Holland",
            "New Tortuga",
            "New Wales",
            "Nifel",
            "Nimbus",
            "Norn",
            "Poseidos",
            "Stormhold",
            "Thrall",
            "Thunder",
            "Trinket",
            "Windblain"
          ],
          "Outfitters": [
            "Basic Outfits"
          ]
        },
        "Zuckungs list/galactic.capital.investment": {
          "Planets": [
            "Sapphire"
          ],
          "Outfitters": [
            "Basic Outfits"
          ]
        },
        "Beccas-Endless-Expansion/Beccas-Endless-Expansion": {
          "Planets": [
            "Haven"
          ],
          "Outfitters": [
            "Basic Outfits"
          ]
        },
        "Galactic War/Galactic-War": {
          "Planets": [
            "Letamos-P382S",
            "Muxkear"
          ],
          "Outfitters": [
            "Basic Outfits"
          ]
        },
        "Lemurias Extra ES Stuff/Lemurias-Extra-ES-Stuff": {
          "Planets": [
            "Barachen",
            "Bardanistra",
            "Denchrao",
            "Eisei",
            "Ekarai",
            "Laateli",
            "Leroo Station",
            "Markaai",
            "Mirdenheim",
            "Ondoristra",
            "Parton",
            "Rodoluki",
            "Sayari Ring",
            "Steirek",
            "Tarsia",
            "Yinachr"
          ],
          "Outfitters": [
            "Basic Outfits"
          ]
        },
        "Mega Freight/Mega-Freight": {
          "Planets": [
            "Ankulah Ship Breaking Station",
            "Vinci"
          ],
          "Outfitters": [
            "Basic Outfits"
          ]
        },
        "sensor/sensor": {
          "Planets": [
            "lidar"
          ],
          "Outfitters": [
            "Basic Outfits"
          ]
        },
        "Lost In Midnight/Lost-in-Midnight": {
          "Planets": [
            "Rum Cellar",
            "Vesta"
          ],
          "Outfitters": [
            "Basic Outfits"
          ]
        },
        "POOT/poot-senza-solaria": {
          "Planets": [
            "Daemonium Solaria Station",
            "Delva Solaris Station",
            "Everything ",
            "Poot ",
            "Ragnarok Solaris Station",
            "Senza Solaria",
            "Ursa Polaris Station II",
            "Valkirus Solaris Station"
          ],
          "Outfitters": [
            "Senza Solaria Plugin Outfits",
            "Senza Solaria Unlockall Outfits Plugin"
          ]
        },
        "POOT/endless_sky_senza_solaria": {
          "Planets": [
            "Daemonium Solaria Station",
            "Delva Solaris Station",
            "Everything ",
            "Poot ",
            "Ragnarok Solaris Station",
            "Senza Solaria",
            "Ursa Polaris Station II",
            "Valkirus Solaris Station"
          ],
          "Outfitters": [
            "Senza Solaria Plugin Outfits",
            "Senza Solaria Unlockall Outfits Plugin"
          ]
        },
        "POOT/poot-senza-solaria_senza_solaria": {
          "Planets": [
            "Daemonium Solaria Station",
            "Delva Solaris Station",
            "Everything ",
            "Poot ",
            "Ragnarok Solaris Station",
            "Senza Solaria",
            "Ursa Polaris Station II",
            "Valkirus Solaris Station"
          ],
          "Outfitters": [
            "Senza Solaria Plugin Outfits",
            "Senza Solaria Unlockall Outfits Plugin"
          ]
        }
      },
      "pluginId": "POOT/poot-infinite-expanse"
    },
    {
      "name": "Infentessimal Outfit Expansion XL",
      "category": "Void Technology",
      "cost": 10000000,
      "thumbnail": "outfit/vanillaplus/infentessimal-outfit",
      "mass": 0,
      "outfit space": 1000,
      "unplunderable": 1,
      "description": "An infinitely small, yet unendingly deep storage device. whenever you look inside of this strange device, its internal storage compartment morphs to mach the outfit attatchment points of your ship.",
      "governments": {
        "Lemurias Extra ES Stuff/Lemurias-Extra-ES-Stuff": {
          "Sayari Plushie": true,
          "Anime Organization": true,
          "Republic": true
        },
        "Mega Freight/Mega-Freight": {
          "Republic": true
        },
        "sensor/sensor": {
          "sensor": true
        },
        "POOT/poot-senza-solaria": {
          "Syndicate": true
        },
        "POOT/endless_sky_senza_solaria": {
          "Syndicate": true
        },
        "POOT/poot-senza-solaria_senza_solaria": {
          "Syndicate": true
        }
      },
      "locations": {
        "official-game/endless-sky": {
          "Planets": [
            "Alfheim",
            "Bivrost",
            "Bloodsea",
            "Clark",
            "Crossroads",
            "Dancer",
            "Delve",
            "Freedom",
            "Furnace",
            "Gagarin",
            "Geyser",
            "Greenwater",
            "Haven",
            "Haze",
            "Heartland",
            "Ingot",
            "Jakobsen",
            "Longjump",
            "Mainsail",
            "Maker",
            "Millrace",
            "Mordente-Bridi",
            "New Argentina",
            "New Boston",
            "New Holland",
            "New Tortuga",
            "New Wales",
            "Nifel",
            "Nimbus",
            "Norn",
            "Poseidos",
            "Stormhold",
            "Thrall",
            "Thunder",
            "Trinket",
            "Windblain"
          ],
          "Outfitters": [
            "Basic Outfits"
          ]
        },
        "Zuckungs list/galactic.capital.investment": {
          "Planets": [
            "Sapphire"
          ],
          "Outfitters": [
            "Basic Outfits"
          ]
        },
        "Beccas-Endless-Expansion/Beccas-Endless-Expansion": {
          "Planets": [
            "Haven"
          ],
          "Outfitters": [
            "Basic Outfits"
          ]
        },
        "Galactic War/Galactic-War": {
          "Planets": [
            "Letamos-P382S",
            "Muxkear"
          ],
          "Outfitters": [
            "Basic Outfits"
          ]
        },
        "Lemurias Extra ES Stuff/Lemurias-Extra-ES-Stuff": {
          "Planets": [
            "Barachen",
            "Bardanistra",
            "Denchrao",
            "Eisei",
            "Ekarai",
            "Laateli",
            "Leroo Station",
            "Markaai",
            "Mirdenheim",
            "Ondoristra",
            "Parton",
            "Rodoluki",
            "Sayari Ring",
            "Steirek",
            "Tarsia",
            "Yinachr"
          ],
          "Outfitters": [
            "Basic Outfits"
          ]
        },
        "Mega Freight/Mega-Freight": {
          "Planets": [
            "Ankulah Ship Breaking Station",
            "Vinci"
          ],
          "Outfitters": [
            "Basic Outfits"
          ]
        },
        "sensor/sensor": {
          "Planets": [
            "lidar"
          ],
          "Outfitters": [
            "Basic Outfits"
          ]
        },
        "Lost In Midnight/Lost-in-Midnight": {
          "Planets": [
            "Rum Cellar",
            "Vesta"
          ],
          "Outfitters": [
            "Basic Outfits"
          ]
        },
        "POOT/poot-senza-solaria": {
          "Planets": [
            "Daemonium Solaria Station",
            "Delva Solaris Station",
            "Everything ",
            "Poot ",
            "Ragnarok Solaris Station",
            "Senza Solaria",
            "Ursa Polaris Station II",
            "Valkirus Solaris Station"
          ],
          "Outfitters": [
            "Senza Solaria Plugin Outfits",
            "Senza Solaria Unlockall Outfits Plugin"
          ]
        },
        "POOT/endless_sky_senza_solaria": {
          "Planets": [
            "Daemonium Solaria Station",
            "Delva Solaris Station",
            "Everything ",
            "Poot ",
            "Ragnarok Solaris Station",
            "Senza Solaria",
            "Ursa Polaris Station II",
            "Valkirus Solaris Station"
          ],
          "Outfitters": [
            "Senza Solaria Plugin Outfits",
            "Senza Solaria Unlockall Outfits Plugin"
          ]
        },
        "POOT/poot-senza-solaria_senza_solaria": {
          "Planets": [
            "Daemonium Solaria Station",
            "Delva Solaris Station",
            "Everything ",
            "Poot ",
            "Ragnarok Solaris Station",
            "Senza Solaria",
            "Ursa Polaris Station II",
            "Valkirus Solaris Station"
          ],
          "Outfitters": [
            "Senza Solaria Plugin Outfits",
            "Senza Solaria Unlockall Outfits Plugin"
          ]
        }
      },
      "pluginId": "POOT/poot-infinite-expanse"
    },
    {
      "name": "Infentessimal Cargo Expansion",
      "category": "Void Technology",
      "cost": 200000,
      "thumbnail": "outfit/vanillaplus/infentessimal-cargo",
      "mass": 0,
      "cargo space": 20,
      "unplunderable": 1,
      "description": "An infinitely small, yet unendingly deep storage device. Whenever you look inside of it, it always seems to be just deep enough to where you can't reach the bottom...",
      "governments": {
        "Lemurias Extra ES Stuff/Lemurias-Extra-ES-Stuff": {
          "Sayari Plushie": true,
          "Anime Organization": true,
          "Republic": true
        },
        "Mega Freight/Mega-Freight": {
          "Republic": true
        },
        "sensor/sensor": {
          "sensor": true
        },
        "POOT/poot-senza-solaria": {
          "Syndicate": true
        },
        "POOT/endless_sky_senza_solaria": {
          "Syndicate": true
        },
        "POOT/poot-senza-solaria_senza_solaria": {
          "Syndicate": true
        }
      },
      "locations": {
        "official-game/endless-sky": {
          "Planets": [
            "Alfheim",
            "Bivrost",
            "Bloodsea",
            "Clark",
            "Crossroads",
            "Dancer",
            "Delve",
            "Freedom",
            "Furnace",
            "Gagarin",
            "Geyser",
            "Greenwater",
            "Haven",
            "Haze",
            "Heartland",
            "Ingot",
            "Jakobsen",
            "Longjump",
            "Mainsail",
            "Maker",
            "Millrace",
            "Mordente-Bridi",
            "New Argentina",
            "New Boston",
            "New Holland",
            "New Tortuga",
            "New Wales",
            "Nifel",
            "Nimbus",
            "Norn",
            "Poseidos",
            "Stormhold",
            "Thrall",
            "Thunder",
            "Trinket",
            "Windblain"
          ],
          "Outfitters": [
            "Basic Outfits"
          ]
        },
        "Zuckungs list/galactic.capital.investment": {
          "Planets": [
            "Sapphire"
          ],
          "Outfitters": [
            "Basic Outfits"
          ]
        },
        "Beccas-Endless-Expansion/Beccas-Endless-Expansion": {
          "Planets": [
            "Haven"
          ],
          "Outfitters": [
            "Basic Outfits"
          ]
        },
        "Galactic War/Galactic-War": {
          "Planets": [
            "Letamos-P382S",
            "Muxkear"
          ],
          "Outfitters": [
            "Basic Outfits"
          ]
        },
        "Lemurias Extra ES Stuff/Lemurias-Extra-ES-Stuff": {
          "Planets": [
            "Barachen",
            "Bardanistra",
            "Denchrao",
            "Eisei",
            "Ekarai",
            "Laateli",
            "Leroo Station",
            "Markaai",
            "Mirdenheim",
            "Ondoristra",
            "Parton",
            "Rodoluki",
            "Sayari Ring",
            "Steirek",
            "Tarsia",
            "Yinachr"
          ],
          "Outfitters": [
            "Basic Outfits"
          ]
        },
        "Mega Freight/Mega-Freight": {
          "Planets": [
            "Ankulah Ship Breaking Station",
            "Vinci"
          ],
          "Outfitters": [
            "Basic Outfits"
          ]
        },
        "sensor/sensor": {
          "Planets": [
            "lidar"
          ],
          "Outfitters": [
            "Basic Outfits"
          ]
        },
        "Lost In Midnight/Lost-in-Midnight": {
          "Planets": [
            "Rum Cellar",
            "Vesta"
          ],
          "Outfitters": [
            "Basic Outfits"
          ]
        },
        "POOT/poot-senza-solaria": {
          "Planets": [
            "Daemonium Solaria Station",
            "Delva Solaris Station",
            "Everything ",
            "Poot ",
            "Ragnarok Solaris Station",
            "Senza Solaria",
            "Ursa Polaris Station II",
            "Valkirus Solaris Station"
          ],
          "Outfitters": [
            "Senza Solaria Plugin Outfits",
            "Senza Solaria Unlockall Outfits Plugin"
          ]
        },
        "POOT/endless_sky_senza_solaria": {
          "Planets": [
            "Daemonium Solaria Station",
            "Delva Solaris Station",
            "Everything ",
            "Poot ",
            "Ragnarok Solaris Station",
            "Senza Solaria",
            "Ursa Polaris Station II",
            "Valkirus Solaris Station"
          ],
          "Outfitters": [
            "Senza Solaria Plugin Outfits",
            "Senza Solaria Unlockall Outfits Plugin"
          ]
        },
        "POOT/poot-senza-solaria_senza_solaria": {
          "Planets": [
            "Daemonium Solaria Station",
            "Delva Solaris Station",
            "Everything ",
            "Poot ",
            "Ragnarok Solaris Station",
            "Senza Solaria",
            "Ursa Polaris Station II",
            "Valkirus Solaris Station"
          ],
          "Outfitters": [
            "Senza Solaria Plugin Outfits",
            "Senza Solaria Unlockall Outfits Plugin"
          ]
        }
      },
      "pluginId": "POOT/poot-infinite-expanse"
    },
    {
      "name": "Infentessimal Cargo Expansion XL",
      "category": "Void Technology",
      "cost": 10000000,
      "thumbnail": "outfit/vanillaplus/infentessimal-cargo",
      "mass": 0,
      "cargo space": 1000,
      "unplunderable": 1,
      "description": "An infinitely small, yet unendingly deep storage device. Whenever you look inside of it, it always seems to be just deep enough to where you can't reach the bottom...",
      "governments": {
        "Lemurias Extra ES Stuff/Lemurias-Extra-ES-Stuff": {
          "Sayari Plushie": true,
          "Anime Organization": true,
          "Republic": true
        },
        "Mega Freight/Mega-Freight": {
          "Republic": true
        },
        "sensor/sensor": {
          "sensor": true
        },
        "POOT/poot-senza-solaria": {
          "Syndicate": true
        },
        "POOT/endless_sky_senza_solaria": {
          "Syndicate": true
        },
        "POOT/poot-senza-solaria_senza_solaria": {
          "Syndicate": true
        }
      },
      "locations": {
        "official-game/endless-sky": {
          "Planets": [
            "Alfheim",
            "Bivrost",
            "Bloodsea",
            "Clark",
            "Crossroads",
            "Dancer",
            "Delve",
            "Freedom",
            "Furnace",
            "Gagarin",
            "Geyser",
            "Greenwater",
            "Haven",
            "Haze",
            "Heartland",
            "Ingot",
            "Jakobsen",
            "Longjump",
            "Mainsail",
            "Maker",
            "Millrace",
            "Mordente-Bridi",
            "New Argentina",
            "New Boston",
            "New Holland",
            "New Tortuga",
            "New Wales",
            "Nifel",
            "Nimbus",
            "Norn",
            "Poseidos",
            "Stormhold",
            "Thrall",
            "Thunder",
            "Trinket",
            "Windblain"
          ],
          "Outfitters": [
            "Basic Outfits"
          ]
        },
        "Zuckungs list/galactic.capital.investment": {
          "Planets": [
            "Sapphire"
          ],
          "Outfitters": [
            "Basic Outfits"
          ]
        },
        "Beccas-Endless-Expansion/Beccas-Endless-Expansion": {
          "Planets": [
            "Haven"
          ],
          "Outfitters": [
            "Basic Outfits"
          ]
        },
        "Galactic War/Galactic-War": {
          "Planets": [
            "Letamos-P382S",
            "Muxkear"
          ],
          "Outfitters": [
            "Basic Outfits"
          ]
        },
        "Lemurias Extra ES Stuff/Lemurias-Extra-ES-Stuff": {
          "Planets": [
            "Barachen",
            "Bardanistra",
            "Denchrao",
            "Eisei",
            "Ekarai",
            "Laateli",
            "Leroo Station",
            "Markaai",
            "Mirdenheim",
            "Ondoristra",
            "Parton",
            "Rodoluki",
            "Sayari Ring",
            "Steirek",
            "Tarsia",
            "Yinachr"
          ],
          "Outfitters": [
            "Basic Outfits"
          ]
        },
        "Mega Freight/Mega-Freight": {
          "Planets": [
            "Ankulah Ship Breaking Station",
            "Vinci"
          ],
          "Outfitters": [
            "Basic Outfits"
          ]
        },
        "sensor/sensor": {
          "Planets": [
            "lidar"
          ],
          "Outfitters": [
            "Basic Outfits"
          ]
        },
        "Lost In Midnight/Lost-in-Midnight": {
          "Planets": [
            "Rum Cellar",
            "Vesta"
          ],
          "Outfitters": [
            "Basic Outfits"
          ]
        },
        "POOT/poot-senza-solaria": {
          "Planets": [
            "Daemonium Solaria Station",
            "Delva Solaris Station",
            "Everything ",
            "Poot ",
            "Ragnarok Solaris Station",
            "Senza Solaria",
            "Ursa Polaris Station II",
            "Valkirus Solaris Station"
          ],
          "Outfitters": [
            "Senza Solaria Plugin Outfits",
            "Senza Solaria Unlockall Outfits Plugin"
          ]
        },
        "POOT/endless_sky_senza_solaria": {
          "Planets": [
            "Daemonium Solaria Station",
            "Delva Solaris Station",
            "Everything ",
            "Poot ",
            "Ragnarok Solaris Station",
            "Senza Solaria",
            "Ursa Polaris Station II",
            "Valkirus Solaris Station"
          ],
          "Outfitters": [
            "Senza Solaria Plugin Outfits",
            "Senza Solaria Unlockall Outfits Plugin"
          ]
        },
        "POOT/poot-senza-solaria_senza_solaria": {
          "Planets": [
            "Daemonium Solaria Station",
            "Delva Solaris Station",
            "Everything ",
            "Poot ",
            "Ragnarok Solaris Station",
            "Senza Solaria",
            "Ursa Polaris Station II",
            "Valkirus Solaris Station"
          ],
          "Outfitters": [
            "Senza Solaria Plugin Outfits",
            "Senza Solaria Unlockall Outfits Plugin"
          ]
        }
      },
      "pluginId": "POOT/poot-infinite-expanse"
    },
    {
      "name": "Void Mass Expansion S",
      "category": "Void Technology",
      "cost": 200000,
      "thumbnail": "outfit/red screwdriver",
      "mass": -25,
      "heat generation": 4.66,
      "unplunderable": 1,
      "description": "By utilizing void technology, this expansion can condense pieces of a ship to reduce their mass by 25. Unforunetly, doing so causes quite a few heating problems.",
      "governments": {
        "Lemurias Extra ES Stuff/Lemurias-Extra-ES-Stuff": {
          "Sayari Plushie": true,
          "Anime Organization": true,
          "Republic": true
        },
        "Mega Freight/Mega-Freight": {
          "Republic": true
        },
        "sensor/sensor": {
          "sensor": true
        },
        "POOT/poot-senza-solaria": {
          "Syndicate": true
        },
        "POOT/endless_sky_senza_solaria": {
          "Syndicate": true
        },
        "POOT/poot-senza-solaria_senza_solaria": {
          "Syndicate": true
        }
      },
      "locations": {
        "official-game/endless-sky": {
          "Planets": [
            "Alfheim",
            "Bivrost",
            "Bloodsea",
            "Clark",
            "Crossroads",
            "Dancer",
            "Delve",
            "Freedom",
            "Furnace",
            "Gagarin",
            "Geyser",
            "Greenwater",
            "Haven",
            "Haze",
            "Heartland",
            "Ingot",
            "Jakobsen",
            "Longjump",
            "Mainsail",
            "Maker",
            "Millrace",
            "Mordente-Bridi",
            "New Argentina",
            "New Boston",
            "New Holland",
            "New Tortuga",
            "New Wales",
            "Nifel",
            "Nimbus",
            "Norn",
            "Poseidos",
            "Stormhold",
            "Thrall",
            "Thunder",
            "Trinket",
            "Windblain"
          ],
          "Outfitters": [
            "Basic Outfits"
          ]
        },
        "Zuckungs list/galactic.capital.investment": {
          "Planets": [
            "Sapphire"
          ],
          "Outfitters": [
            "Basic Outfits"
          ]
        },
        "Beccas-Endless-Expansion/Beccas-Endless-Expansion": {
          "Planets": [
            "Haven"
          ],
          "Outfitters": [
            "Basic Outfits"
          ]
        },
        "Galactic War/Galactic-War": {
          "Planets": [
            "Letamos-P382S",
            "Muxkear"
          ],
          "Outfitters": [
            "Basic Outfits"
          ]
        },
        "Lemurias Extra ES Stuff/Lemurias-Extra-ES-Stuff": {
          "Planets": [
            "Barachen",
            "Bardanistra",
            "Denchrao",
            "Eisei",
            "Ekarai",
            "Laateli",
            "Leroo Station",
            "Markaai",
            "Mirdenheim",
            "Ondoristra",
            "Parton",
            "Rodoluki",
            "Sayari Ring",
            "Steirek",
            "Tarsia",
            "Yinachr"
          ],
          "Outfitters": [
            "Basic Outfits"
          ]
        },
        "Mega Freight/Mega-Freight": {
          "Planets": [
            "Ankulah Ship Breaking Station",
            "Vinci"
          ],
          "Outfitters": [
            "Basic Outfits"
          ]
        },
        "sensor/sensor": {
          "Planets": [
            "lidar"
          ],
          "Outfitters": [
            "Basic Outfits"
          ]
        },
        "Lost In Midnight/Lost-in-Midnight": {
          "Planets": [
            "Rum Cellar",
            "Vesta"
          ],
          "Outfitters": [
            "Basic Outfits"
          ]
        },
        "POOT/poot-senza-solaria": {
          "Planets": [
            "Daemonium Solaria Station",
            "Delva Solaris Station",
            "Everything ",
            "Poot ",
            "Ragnarok Solaris Station",
            "Senza Solaria",
            "Ursa Polaris Station II",
            "Valkirus Solaris Station"
          ],
          "Outfitters": [
            "Senza Solaria Plugin Outfits",
            "Senza Solaria Unlockall Outfits Plugin"
          ]
        },
        "POOT/endless_sky_senza_solaria": {
          "Planets": [
            "Daemonium Solaria Station",
            "Delva Solaris Station",
            "Everything ",
            "Poot ",
            "Ragnarok Solaris Station",
            "Senza Solaria",
            "Ursa Polaris Station II",
            "Valkirus Solaris Station"
          ],
          "Outfitters": [
            "Senza Solaria Plugin Outfits",
            "Senza Solaria Unlockall Outfits Plugin"
          ]
        },
        "POOT/poot-senza-solaria_senza_solaria": {
          "Planets": [
            "Daemonium Solaria Station",
            "Delva Solaris Station",
            "Everything ",
            "Poot ",
            "Ragnarok Solaris Station",
            "Senza Solaria",
            "Ursa Polaris Station II",
            "Valkirus Solaris Station"
          ],
          "Outfitters": [
            "Senza Solaria Plugin Outfits",
            "Senza Solaria Unlockall Outfits Plugin"
          ]
        }
      },
      "pluginId": "POOT/poot-infinite-expanse"
    },
    {
      "name": "Void Mass Expansion XL",
      "category": "Void Technology",
      "cost": 20000000,
      "thumbnail": "outfit/red screwdriver",
      "mass": -2500,
      "heat generation": 466,
      "unplunderable": 1,
      "description": "By utilizing void technology, this expansion can condense pieces of a ship to reduce their mass by 25. Unforunetly, doing so causes quite a few heating problems.",
      "governments": {
        "Lemurias Extra ES Stuff/Lemurias-Extra-ES-Stuff": {
          "Sayari Plushie": true,
          "Anime Organization": true,
          "Republic": true
        },
        "Mega Freight/Mega-Freight": {
          "Republic": true
        },
        "sensor/sensor": {
          "sensor": true
        },
        "POOT/poot-senza-solaria": {
          "Syndicate": true
        },
        "POOT/endless_sky_senza_solaria": {
          "Syndicate": true
        },
        "POOT/poot-senza-solaria_senza_solaria": {
          "Syndicate": true
        }
      },
      "locations": {
        "official-game/endless-sky": {
          "Planets": [
            "Alfheim",
            "Bivrost",
            "Bloodsea",
            "Clark",
            "Crossroads",
            "Dancer",
            "Delve",
            "Freedom",
            "Furnace",
            "Gagarin",
            "Geyser",
            "Greenwater",
            "Haven",
            "Haze",
            "Heartland",
            "Ingot",
            "Jakobsen",
            "Longjump",
            "Mainsail",
            "Maker",
            "Millrace",
            "Mordente-Bridi",
            "New Argentina",
            "New Boston",
            "New Holland",
            "New Tortuga",
            "New Wales",
            "Nifel",
            "Nimbus",
            "Norn",
            "Poseidos",
            "Stormhold",
            "Thrall",
            "Thunder",
            "Trinket",
            "Windblain"
          ],
          "Outfitters": [
            "Basic Outfits"
          ]
        },
        "Zuckungs list/galactic.capital.investment": {
          "Planets": [
            "Sapphire"
          ],
          "Outfitters": [
            "Basic Outfits"
          ]
        },
        "Beccas-Endless-Expansion/Beccas-Endless-Expansion": {
          "Planets": [
            "Haven"
          ],
          "Outfitters": [
            "Basic Outfits"
          ]
        },
        "Galactic War/Galactic-War": {
          "Planets": [
            "Letamos-P382S",
            "Muxkear"
          ],
          "Outfitters": [
            "Basic Outfits"
          ]
        },
        "Lemurias Extra ES Stuff/Lemurias-Extra-ES-Stuff": {
          "Planets": [
            "Barachen",
            "Bardanistra",
            "Denchrao",
            "Eisei",
            "Ekarai",
            "Laateli",
            "Leroo Station",
            "Markaai",
            "Mirdenheim",
            "Ondoristra",
            "Parton",
            "Rodoluki",
            "Sayari Ring",
            "Steirek",
            "Tarsia",
            "Yinachr"
          ],
          "Outfitters": [
            "Basic Outfits"
          ]
        },
        "Mega Freight/Mega-Freight": {
          "Planets": [
            "Ankulah Ship Breaking Station",
            "Vinci"
          ],
          "Outfitters": [
            "Basic Outfits"
          ]
        },
        "sensor/sensor": {
          "Planets": [
            "lidar"
          ],
          "Outfitters": [
            "Basic Outfits"
          ]
        },
        "Lost In Midnight/Lost-in-Midnight": {
          "Planets": [
            "Rum Cellar",
            "Vesta"
          ],
          "Outfitters": [
            "Basic Outfits"
          ]
        },
        "POOT/poot-senza-solaria": {
          "Planets": [
            "Daemonium Solaria Station",
            "Delva Solaris Station",
            "Everything ",
            "Poot ",
            "Ragnarok Solaris Station",
            "Senza Solaria",
            "Ursa Polaris Station II",
            "Valkirus Solaris Station"
          ],
          "Outfitters": [
            "Senza Solaria Plugin Outfits",
            "Senza Solaria Unlockall Outfits Plugin"
          ]
        },
        "POOT/endless_sky_senza_solaria": {
          "Planets": [
            "Daemonium Solaria Station",
            "Delva Solaris Station",
            "Everything ",
            "Poot ",
            "Ragnarok Solaris Station",
            "Senza Solaria",
            "Ursa Polaris Station II",
            "Valkirus Solaris Station"
          ],
          "Outfitters": [
            "Senza Solaria Plugin Outfits",
            "Senza Solaria Unlockall Outfits Plugin"
          ]
        },
        "POOT/poot-senza-solaria_senza_solaria": {
          "Planets": [
            "Daemonium Solaria Station",
            "Delva Solaris Station",
            "Everything ",
            "Poot ",
            "Ragnarok Solaris Station",
            "Senza Solaria",
            "Ursa Polaris Station II",
            "Valkirus Solaris Station"
          ],
          "Outfitters": [
            "Senza Solaria Plugin Outfits",
            "Senza Solaria Unlockall Outfits Plugin"
          ]
        }
      },
      "pluginId": "POOT/poot-infinite-expanse"
    },
    {
      "name": "Void Outfit Expansion S",
      "category": "Void Technology",
      "cost": 160000,
      "thumbnail": "outfit/green screwdriver",
      "mass": 10,
      "outfit space": 20,
      "cargo space": -5,
      "heat generation": 2.25,
      "unplunderable": 1,
      "description": "By utilizing void technology, this expansion increases outfit space by 20 at the cost of 5 cargo space.",
      "governments": {
        "Lemurias Extra ES Stuff/Lemurias-Extra-ES-Stuff": {
          "Sayari Plushie": true,
          "Anime Organization": true,
          "Republic": true
        },
        "Mega Freight/Mega-Freight": {
          "Republic": true
        },
        "sensor/sensor": {
          "sensor": true
        },
        "POOT/poot-senza-solaria": {
          "Syndicate": true
        },
        "POOT/endless_sky_senza_solaria": {
          "Syndicate": true
        },
        "POOT/poot-senza-solaria_senza_solaria": {
          "Syndicate": true
        }
      },
      "locations": {
        "official-game/endless-sky": {
          "Planets": [
            "Alfheim",
            "Bivrost",
            "Bloodsea",
            "Clark",
            "Crossroads",
            "Dancer",
            "Delve",
            "Freedom",
            "Furnace",
            "Gagarin",
            "Geyser",
            "Greenwater",
            "Haven",
            "Haze",
            "Heartland",
            "Ingot",
            "Jakobsen",
            "Longjump",
            "Mainsail",
            "Maker",
            "Millrace",
            "Mordente-Bridi",
            "New Argentina",
            "New Boston",
            "New Holland",
            "New Tortuga",
            "New Wales",
            "Nifel",
            "Nimbus",
            "Norn",
            "Poseidos",
            "Stormhold",
            "Thrall",
            "Thunder",
            "Trinket",
            "Windblain"
          ],
          "Outfitters": [
            "Basic Outfits"
          ]
        },
        "Zuckungs list/galactic.capital.investment": {
          "Planets": [
            "Sapphire"
          ],
          "Outfitters": [
            "Basic Outfits"
          ]
        },
        "Beccas-Endless-Expansion/Beccas-Endless-Expansion": {
          "Planets": [
            "Haven"
          ],
          "Outfitters": [
            "Basic Outfits"
          ]
        },
        "Galactic War/Galactic-War": {
          "Planets": [
            "Letamos-P382S",
            "Muxkear"
          ],
          "Outfitters": [
            "Basic Outfits"
          ]
        },
        "Lemurias Extra ES Stuff/Lemurias-Extra-ES-Stuff": {
          "Planets": [
            "Barachen",
            "Bardanistra",
            "Denchrao",
            "Eisei",
            "Ekarai",
            "Laateli",
            "Leroo Station",
            "Markaai",
            "Mirdenheim",
            "Ondoristra",
            "Parton",
            "Rodoluki",
            "Sayari Ring",
            "Steirek",
            "Tarsia",
            "Yinachr"
          ],
          "Outfitters": [
            "Basic Outfits"
          ]
        },
        "Mega Freight/Mega-Freight": {
          "Planets": [
            "Ankulah Ship Breaking Station",
            "Vinci"
          ],
          "Outfitters": [
            "Basic Outfits"
          ]
        },
        "sensor/sensor": {
          "Planets": [
            "lidar"
          ],
          "Outfitters": [
            "Basic Outfits"
          ]
        },
        "Lost In Midnight/Lost-in-Midnight": {
          "Planets": [
            "Rum Cellar",
            "Vesta"
          ],
          "Outfitters": [
            "Basic Outfits"
          ]
        },
        "POOT/poot-senza-solaria": {
          "Planets": [
            "Daemonium Solaria Station",
            "Delva Solaris Station",
            "Everything ",
            "Poot ",
            "Ragnarok Solaris Station",
            "Senza Solaria",
            "Ursa Polaris Station II",
            "Valkirus Solaris Station"
          ],
          "Outfitters": [
            "Senza Solaria Plugin Outfits",
            "Senza Solaria Unlockall Outfits Plugin"
          ]
        },
        "POOT/endless_sky_senza_solaria": {
          "Planets": [
            "Daemonium Solaria Station",
            "Delva Solaris Station",
            "Everything ",
            "Poot ",
            "Ragnarok Solaris Station",
            "Senza Solaria",
            "Ursa Polaris Station II",
            "Valkirus Solaris Station"
          ],
          "Outfitters": [
            "Senza Solaria Plugin Outfits",
            "Senza Solaria Unlockall Outfits Plugin"
          ]
        },
        "POOT/poot-senza-solaria_senza_solaria": {
          "Planets": [
            "Daemonium Solaria Station",
            "Delva Solaris Station",
            "Everything ",
            "Poot ",
            "Ragnarok Solaris Station",
            "Senza Solaria",
            "Ursa Polaris Station II",
            "Valkirus Solaris Station"
          ],
          "Outfitters": [
            "Senza Solaria Plugin Outfits",
            "Senza Solaria Unlockall Outfits Plugin"
          ]
        }
      },
      "pluginId": "POOT/poot-infinite-expanse"
    },
    {
      "name": "Void Outfit Expansion XL",
      "category": "Void Technology",
      "cost": 16000000,
      "thumbnail": "outfit/green screwdriver",
      "mass": 1000,
      "outfit space": 2000,
      "cargo space": -500,
      "heat generation": 225,
      "unplunderable": 1,
      "description": "By utilizing void technology, this expansion increases outfit space by 2000 at the cost of 500 cargo space.",
      "governments": {
        "Lemurias Extra ES Stuff/Lemurias-Extra-ES-Stuff": {
          "Sayari Plushie": true,
          "Anime Organization": true,
          "Republic": true
        },
        "Mega Freight/Mega-Freight": {
          "Republic": true
        },
        "sensor/sensor": {
          "sensor": true
        },
        "POOT/poot-senza-solaria": {
          "Syndicate": true
        },
        "POOT/endless_sky_senza_solaria": {
          "Syndicate": true
        },
        "POOT/poot-senza-solaria_senza_solaria": {
          "Syndicate": true
        }
      },
      "locations": {
        "official-game/endless-sky": {
          "Planets": [
            "Alfheim",
            "Bivrost",
            "Bloodsea",
            "Clark",
            "Crossroads",
            "Dancer",
            "Delve",
            "Freedom",
            "Furnace",
            "Gagarin",
            "Geyser",
            "Greenwater",
            "Haven",
            "Haze",
            "Heartland",
            "Ingot",
            "Jakobsen",
            "Longjump",
            "Mainsail",
            "Maker",
            "Millrace",
            "Mordente-Bridi",
            "New Argentina",
            "New Boston",
            "New Holland",
            "New Tortuga",
            "New Wales",
            "Nifel",
            "Nimbus",
            "Norn",
            "Poseidos",
            "Stormhold",
            "Thrall",
            "Thunder",
            "Trinket",
            "Windblain"
          ],
          "Outfitters": [
            "Basic Outfits"
          ]
        },
        "Zuckungs list/galactic.capital.investment": {
          "Planets": [
            "Sapphire"
          ],
          "Outfitters": [
            "Basic Outfits"
          ]
        },
        "Beccas-Endless-Expansion/Beccas-Endless-Expansion": {
          "Planets": [
            "Haven"
          ],
          "Outfitters": [
            "Basic Outfits"
          ]
        },
        "Galactic War/Galactic-War": {
          "Planets": [
            "Letamos-P382S",
            "Muxkear"
          ],
          "Outfitters": [
            "Basic Outfits"
          ]
        },
        "Lemurias Extra ES Stuff/Lemurias-Extra-ES-Stuff": {
          "Planets": [
            "Barachen",
            "Bardanistra",
            "Denchrao",
            "Eisei",
            "Ekarai",
            "Laateli",
            "Leroo Station",
            "Markaai",
            "Mirdenheim",
            "Ondoristra",
            "Parton",
            "Rodoluki",
            "Sayari Ring",
            "Steirek",
            "Tarsia",
            "Yinachr"
          ],
          "Outfitters": [
            "Basic Outfits"
          ]
        },
        "Mega Freight/Mega-Freight": {
          "Planets": [
            "Ankulah Ship Breaking Station",
            "Vinci"
          ],
          "Outfitters": [
            "Basic Outfits"
          ]
        },
        "sensor/sensor": {
          "Planets": [
            "lidar"
          ],
          "Outfitters": [
            "Basic Outfits"
          ]
        },
        "Lost In Midnight/Lost-in-Midnight": {
          "Planets": [
            "Rum Cellar",
            "Vesta"
          ],
          "Outfitters": [
            "Basic Outfits"
          ]
        },
        "POOT/poot-senza-solaria": {
          "Planets": [
            "Daemonium Solaria Station",
            "Delva Solaris Station",
            "Everything ",
            "Poot ",
            "Ragnarok Solaris Station",
            "Senza Solaria",
            "Ursa Polaris Station II",
            "Valkirus Solaris Station"
          ],
          "Outfitters": [
            "Senza Solaria Plugin Outfits",
            "Senza Solaria Unlockall Outfits Plugin"
          ]
        },
        "POOT/endless_sky_senza_solaria": {
          "Planets": [
            "Daemonium Solaria Station",
            "Delva Solaris Station",
            "Everything ",
            "Poot ",
            "Ragnarok Solaris Station",
            "Senza Solaria",
            "Ursa Polaris Station II",
            "Valkirus Solaris Station"
          ],
          "Outfitters": [
            "Senza Solaria Plugin Outfits",
            "Senza Solaria Unlockall Outfits Plugin"
          ]
        },
        "POOT/poot-senza-solaria_senza_solaria": {
          "Planets": [
            "Daemonium Solaria Station",
            "Delva Solaris Station",
            "Everything ",
            "Poot ",
            "Ragnarok Solaris Station",
            "Senza Solaria",
            "Ursa Polaris Station II",
            "Valkirus Solaris Station"
          ],
          "Outfitters": [
            "Senza Solaria Plugin Outfits",
            "Senza Solaria Unlockall Outfits Plugin"
          ]
        }
      },
      "pluginId": "POOT/poot-infinite-expanse"
    },
    {
      "name": "Void Cargo Expansion S",
      "category": "Void Technology",
      "cost": 400000,
      "thumbnail": "outfit/purple screwdriver",
      "mass": 30,
      "cargo space": 20,
      "outfit space": -5,
      "heat generation": 2,
      "unplunderable": 1,
      "description": "By utilizing void technology, this expansion increases cargo space by 2000 at the cost of 500 Outfit Space. The expansion does, however, cause some heat inefficiency.",
      "governments": {
        "Lemurias Extra ES Stuff/Lemurias-Extra-ES-Stuff": {
          "Sayari Plushie": true,
          "Anime Organization": true,
          "Republic": true
        },
        "Mega Freight/Mega-Freight": {
          "Republic": true
        },
        "sensor/sensor": {
          "sensor": true
        },
        "POOT/poot-senza-solaria": {
          "Syndicate": true
        },
        "POOT/endless_sky_senza_solaria": {
          "Syndicate": true
        },
        "POOT/poot-senza-solaria_senza_solaria": {
          "Syndicate": true
        }
      },
      "locations": {
        "official-game/endless-sky": {
          "Planets": [
            "Alfheim",
            "Bivrost",
            "Bloodsea",
            "Clark",
            "Crossroads",
            "Dancer",
            "Delve",
            "Freedom",
            "Furnace",
            "Gagarin",
            "Geyser",
            "Greenwater",
            "Haven",
            "Haze",
            "Heartland",
            "Ingot",
            "Jakobsen",
            "Longjump",
            "Mainsail",
            "Maker",
            "Millrace",
            "Mordente-Bridi",
            "New Argentina",
            "New Boston",
            "New Holland",
            "New Tortuga",
            "New Wales",
            "Nifel",
            "Nimbus",
            "Norn",
            "Poseidos",
            "Stormhold",
            "Thrall",
            "Thunder",
            "Trinket",
            "Windblain"
          ],
          "Outfitters": [
            "Basic Outfits"
          ]
        },
        "Zuckungs list/galactic.capital.investment": {
          "Planets": [
            "Sapphire"
          ],
          "Outfitters": [
            "Basic Outfits"
          ]
        },
        "Beccas-Endless-Expansion/Beccas-Endless-Expansion": {
          "Planets": [
            "Haven"
          ],
          "Outfitters": [
            "Basic Outfits"
          ]
        },
        "Galactic War/Galactic-War": {
          "Planets": [
            "Letamos-P382S",
            "Muxkear"
          ],
          "Outfitters": [
            "Basic Outfits"
          ]
        },
        "Lemurias Extra ES Stuff/Lemurias-Extra-ES-Stuff": {
          "Planets": [
            "Barachen",
            "Bardanistra",
            "Denchrao",
            "Eisei",
            "Ekarai",
            "Laateli",
            "Leroo Station",
            "Markaai",
            "Mirdenheim",
            "Ondoristra",
            "Parton",
            "Rodoluki",
            "Sayari Ring",
            "Steirek",
            "Tarsia",
            "Yinachr"
          ],
          "Outfitters": [
            "Basic Outfits"
          ]
        },
        "Mega Freight/Mega-Freight": {
          "Planets": [
            "Ankulah Ship Breaking Station",
            "Vinci"
          ],
          "Outfitters": [
            "Basic Outfits"
          ]
        },
        "sensor/sensor": {
          "Planets": [
            "lidar"
          ],
          "Outfitters": [
            "Basic Outfits"
          ]
        },
        "Lost In Midnight/Lost-in-Midnight": {
          "Planets": [
            "Rum Cellar",
            "Vesta"
          ],
          "Outfitters": [
            "Basic Outfits"
          ]
        },
        "POOT/poot-senza-solaria": {
          "Planets": [
            "Daemonium Solaria Station",
            "Delva Solaris Station",
            "Everything ",
            "Poot ",
            "Ragnarok Solaris Station",
            "Senza Solaria",
            "Ursa Polaris Station II",
            "Valkirus Solaris Station"
          ],
          "Outfitters": [
            "Senza Solaria Plugin Outfits",
            "Senza Solaria Unlockall Outfits Plugin"
          ]
        },
        "POOT/endless_sky_senza_solaria": {
          "Planets": [
            "Daemonium Solaria Station",
            "Delva Solaris Station",
            "Everything ",
            "Poot ",
            "Ragnarok Solaris Station",
            "Senza Solaria",
            "Ursa Polaris Station II",
            "Valkirus Solaris Station"
          ],
          "Outfitters": [
            "Senza Solaria Plugin Outfits",
            "Senza Solaria Unlockall Outfits Plugin"
          ]
        },
        "POOT/poot-senza-solaria_senza_solaria": {
          "Planets": [
            "Daemonium Solaria Station",
            "Delva Solaris Station",
            "Everything ",
            "Poot ",
            "Ragnarok Solaris Station",
            "Senza Solaria",
            "Ursa Polaris Station II",
            "Valkirus Solaris Station"
          ],
          "Outfitters": [
            "Senza Solaria Plugin Outfits",
            "Senza Solaria Unlockall Outfits Plugin"
          ]
        }
      },
      "pluginId": "POOT/poot-infinite-expanse"
    },
    {
      "name": "Void Cargo Expansion XL",
      "category": "Void Technology",
      "cost": 40000000,
      "thumbnail": "outfit/purple screwdriver",
      "mass": 3000,
      "cargo space": 2000,
      "outfit space": -500,
      "heat generation": 200,
      "unplunderable": 1,
      "description": "By utilizing void technology, this expansion increases cargo space by 2000 at the cost of 500 Outfit Space. The expansion does, however, cause some heat inefficiency.",
      "governments": {
        "Lemurias Extra ES Stuff/Lemurias-Extra-ES-Stuff": {
          "Sayari Plushie": true,
          "Anime Organization": true,
          "Republic": true
        },
        "Mega Freight/Mega-Freight": {
          "Republic": true
        },
        "sensor/sensor": {
          "sensor": true
        },
        "POOT/poot-senza-solaria": {
          "Syndicate": true
        },
        "POOT/endless_sky_senza_solaria": {
          "Syndicate": true
        },
        "POOT/poot-senza-solaria_senza_solaria": {
          "Syndicate": true
        }
      },
      "locations": {
        "official-game/endless-sky": {
          "Planets": [
            "Alfheim",
            "Bivrost",
            "Bloodsea",
            "Clark",
            "Crossroads",
            "Dancer",
            "Delve",
            "Freedom",
            "Furnace",
            "Gagarin",
            "Geyser",
            "Greenwater",
            "Haven",
            "Haze",
            "Heartland",
            "Ingot",
            "Jakobsen",
            "Longjump",
            "Mainsail",
            "Maker",
            "Millrace",
            "Mordente-Bridi",
            "New Argentina",
            "New Boston",
            "New Holland",
            "New Tortuga",
            "New Wales",
            "Nifel",
            "Nimbus",
            "Norn",
            "Poseidos",
            "Stormhold",
            "Thrall",
            "Thunder",
            "Trinket",
            "Windblain"
          ],
          "Outfitters": [
            "Basic Outfits"
          ]
        },
        "Zuckungs list/galactic.capital.investment": {
          "Planets": [
            "Sapphire"
          ],
          "Outfitters": [
            "Basic Outfits"
          ]
        },
        "Beccas-Endless-Expansion/Beccas-Endless-Expansion": {
          "Planets": [
            "Haven"
          ],
          "Outfitters": [
            "Basic Outfits"
          ]
        },
        "Galactic War/Galactic-War": {
          "Planets": [
            "Letamos-P382S",
            "Muxkear"
          ],
          "Outfitters": [
            "Basic Outfits"
          ]
        },
        "Lemurias Extra ES Stuff/Lemurias-Extra-ES-Stuff": {
          "Planets": [
            "Barachen",
            "Bardanistra",
            "Denchrao",
            "Eisei",
            "Ekarai",
            "Laateli",
            "Leroo Station",
            "Markaai",
            "Mirdenheim",
            "Ondoristra",
            "Parton",
            "Rodoluki",
            "Sayari Ring",
            "Steirek",
            "Tarsia",
            "Yinachr"
          ],
          "Outfitters": [
            "Basic Outfits"
          ]
        },
        "Mega Freight/Mega-Freight": {
          "Planets": [
            "Ankulah Ship Breaking Station",
            "Vinci"
          ],
          "Outfitters": [
            "Basic Outfits"
          ]
        },
        "sensor/sensor": {
          "Planets": [
            "lidar"
          ],
          "Outfitters": [
            "Basic Outfits"
          ]
        },
        "Lost In Midnight/Lost-in-Midnight": {
          "Planets": [
            "Rum Cellar",
            "Vesta"
          ],
          "Outfitters": [
            "Basic Outfits"
          ]
        },
        "POOT/poot-senza-solaria": {
          "Planets": [
            "Daemonium Solaria Station",
            "Delva Solaris Station",
            "Everything ",
            "Poot ",
            "Ragnarok Solaris Station",
            "Senza Solaria",
            "Ursa Polaris Station II",
            "Valkirus Solaris Station"
          ],
          "Outfitters": [
            "Senza Solaria Plugin Outfits",
            "Senza Solaria Unlockall Outfits Plugin"
          ]
        },
        "POOT/endless_sky_senza_solaria": {
          "Planets": [
            "Daemonium Solaria Station",
            "Delva Solaris Station",
            "Everything ",
            "Poot ",
            "Ragnarok Solaris Station",
            "Senza Solaria",
            "Ursa Polaris Station II",
            "Valkirus Solaris Station"
          ],
          "Outfitters": [
            "Senza Solaria Plugin Outfits",
            "Senza Solaria Unlockall Outfits Plugin"
          ]
        },
        "POOT/poot-senza-solaria_senza_solaria": {
          "Planets": [
            "Daemonium Solaria Station",
            "Delva Solaris Station",
            "Everything ",
            "Poot ",
            "Ragnarok Solaris Station",
            "Senza Solaria",
            "Ursa Polaris Station II",
            "Valkirus Solaris Station"
          ],
          "Outfitters": [
            "Senza Solaria Plugin Outfits",
            "Senza Solaria Unlockall Outfits Plugin"
          ]
        }
      },
      "pluginId": "POOT/poot-infinite-expanse"
    },
    {
      "name": "Void Engine Expansion S",
      "category": "Void Technology",
      "cost": 160000,
      "thumbnail": "outfit/orange screwdriver",
      "mass": 20,
      "outfit space": -5,
      "engine capacity": 20,
      "unplunderable": 1,
      "heat generation": 1.5,
      "description": "By utilizing void technology, this expansion increases engine capacity by 20 at the cost of 5 Outfit Space.",
      "governments": {
        "Lemurias Extra ES Stuff/Lemurias-Extra-ES-Stuff": {
          "Sayari Plushie": true,
          "Anime Organization": true,
          "Republic": true
        },
        "Mega Freight/Mega-Freight": {
          "Republic": true
        },
        "sensor/sensor": {
          "sensor": true
        },
        "POOT/poot-senza-solaria": {
          "Syndicate": true
        },
        "POOT/endless_sky_senza_solaria": {
          "Syndicate": true
        },
        "POOT/poot-senza-solaria_senza_solaria": {
          "Syndicate": true
        }
      },
      "locations": {
        "official-game/endless-sky": {
          "Planets": [
            "Alfheim",
            "Bivrost",
            "Bloodsea",
            "Clark",
            "Crossroads",
            "Dancer",
            "Delve",
            "Freedom",
            "Furnace",
            "Gagarin",
            "Geyser",
            "Greenwater",
            "Haven",
            "Haze",
            "Heartland",
            "Ingot",
            "Jakobsen",
            "Longjump",
            "Mainsail",
            "Maker",
            "Millrace",
            "Mordente-Bridi",
            "New Argentina",
            "New Boston",
            "New Holland",
            "New Tortuga",
            "New Wales",
            "Nifel",
            "Nimbus",
            "Norn",
            "Poseidos",
            "Stormhold",
            "Thrall",
            "Thunder",
            "Trinket",
            "Windblain"
          ],
          "Outfitters": [
            "Basic Outfits"
          ]
        },
        "Zuckungs list/galactic.capital.investment": {
          "Planets": [
            "Sapphire"
          ],
          "Outfitters": [
            "Basic Outfits"
          ]
        },
        "Beccas-Endless-Expansion/Beccas-Endless-Expansion": {
          "Planets": [
            "Haven"
          ],
          "Outfitters": [
            "Basic Outfits"
          ]
        },
        "Galactic War/Galactic-War": {
          "Planets": [
            "Letamos-P382S",
            "Muxkear"
          ],
          "Outfitters": [
            "Basic Outfits"
          ]
        },
        "Lemurias Extra ES Stuff/Lemurias-Extra-ES-Stuff": {
          "Planets": [
            "Barachen",
            "Bardanistra",
            "Denchrao",
            "Eisei",
            "Ekarai",
            "Laateli",
            "Leroo Station",
            "Markaai",
            "Mirdenheim",
            "Ondoristra",
            "Parton",
            "Rodoluki",
            "Sayari Ring",
            "Steirek",
            "Tarsia",
            "Yinachr"
          ],
          "Outfitters": [
            "Basic Outfits"
          ]
        },
        "Mega Freight/Mega-Freight": {
          "Planets": [
            "Ankulah Ship Breaking Station",
            "Vinci"
          ],
          "Outfitters": [
            "Basic Outfits"
          ]
        },
        "sensor/sensor": {
          "Planets": [
            "lidar"
          ],
          "Outfitters": [
            "Basic Outfits"
          ]
        },
        "Lost In Midnight/Lost-in-Midnight": {
          "Planets": [
            "Rum Cellar",
            "Vesta"
          ],
          "Outfitters": [
            "Basic Outfits"
          ]
        },
        "POOT/poot-senza-solaria": {
          "Planets": [
            "Daemonium Solaria Station",
            "Delva Solaris Station",
            "Everything ",
            "Poot ",
            "Ragnarok Solaris Station",
            "Senza Solaria",
            "Ursa Polaris Station II",
            "Valkirus Solaris Station"
          ],
          "Outfitters": [
            "Senza Solaria Plugin Outfits",
            "Senza Solaria Unlockall Outfits Plugin"
          ]
        },
        "POOT/endless_sky_senza_solaria": {
          "Planets": [
            "Daemonium Solaria Station",
            "Delva Solaris Station",
            "Everything ",
            "Poot ",
            "Ragnarok Solaris Station",
            "Senza Solaria",
            "Ursa Polaris Station II",
            "Valkirus Solaris Station"
          ],
          "Outfitters": [
            "Senza Solaria Plugin Outfits",
            "Senza Solaria Unlockall Outfits Plugin"
          ]
        },
        "POOT/poot-senza-solaria_senza_solaria": {
          "Planets": [
            "Daemonium Solaria Station",
            "Delva Solaris Station",
            "Everything ",
            "Poot ",
            "Ragnarok Solaris Station",
            "Senza Solaria",
            "Ursa Polaris Station II",
            "Valkirus Solaris Station"
          ],
          "Outfitters": [
            "Senza Solaria Plugin Outfits",
            "Senza Solaria Unlockall Outfits Plugin"
          ]
        }
      },
      "pluginId": "POOT/poot-infinite-expanse"
    },
    {
      "name": "Void Engine Expansion XL",
      "category": "Void Technology",
      "cost": 16000000,
      "thumbnail": "outfit/orange screwdriver",
      "mass": 2000,
      "outfit space": -500,
      "engine capacity": 2000,
      "heat generation": 150,
      "unplunderable": 1,
      "description": "By utilizing void technology, this expansion increases engine capacity by 2000 at the cost of 500 Outfit Space.",
      "governments": {
        "Lemurias Extra ES Stuff/Lemurias-Extra-ES-Stuff": {
          "Sayari Plushie": true,
          "Anime Organization": true,
          "Republic": true
        },
        "Mega Freight/Mega-Freight": {
          "Republic": true
        },
        "sensor/sensor": {
          "sensor": true
        },
        "POOT/poot-senza-solaria": {
          "Syndicate": true
        },
        "POOT/endless_sky_senza_solaria": {
          "Syndicate": true
        },
        "POOT/poot-senza-solaria_senza_solaria": {
          "Syndicate": true
        }
      },
      "locations": {
        "official-game/endless-sky": {
          "Planets": [
            "Alfheim",
            "Bivrost",
            "Bloodsea",
            "Clark",
            "Crossroads",
            "Dancer",
            "Delve",
            "Freedom",
            "Furnace",
            "Gagarin",
            "Geyser",
            "Greenwater",
            "Haven",
            "Haze",
            "Heartland",
            "Ingot",
            "Jakobsen",
            "Longjump",
            "Mainsail",
            "Maker",
            "Millrace",
            "Mordente-Bridi",
            "New Argentina",
            "New Boston",
            "New Holland",
            "New Tortuga",
            "New Wales",
            "Nifel",
            "Nimbus",
            "Norn",
            "Poseidos",
            "Stormhold",
            "Thrall",
            "Thunder",
            "Trinket",
            "Windblain"
          ],
          "Outfitters": [
            "Basic Outfits"
          ]
        },
        "Zuckungs list/galactic.capital.investment": {
          "Planets": [
            "Sapphire"
          ],
          "Outfitters": [
            "Basic Outfits"
          ]
        },
        "Beccas-Endless-Expansion/Beccas-Endless-Expansion": {
          "Planets": [
            "Haven"
          ],
          "Outfitters": [
            "Basic Outfits"
          ]
        },
        "Galactic War/Galactic-War": {
          "Planets": [
            "Letamos-P382S",
            "Muxkear"
          ],
          "Outfitters": [
            "Basic Outfits"
          ]
        },
        "Lemurias Extra ES Stuff/Lemurias-Extra-ES-Stuff": {
          "Planets": [
            "Barachen",
            "Bardanistra",
            "Denchrao",
            "Eisei",
            "Ekarai",
            "Laateli",
            "Leroo Station",
            "Markaai",
            "Mirdenheim",
            "Ondoristra",
            "Parton",
            "Rodoluki",
            "Sayari Ring",
            "Steirek",
            "Tarsia",
            "Yinachr"
          ],
          "Outfitters": [
            "Basic Outfits"
          ]
        },
        "Mega Freight/Mega-Freight": {
          "Planets": [
            "Ankulah Ship Breaking Station",
            "Vinci"
          ],
          "Outfitters": [
            "Basic Outfits"
          ]
        },
        "sensor/sensor": {
          "Planets": [
            "lidar"
          ],
          "Outfitters": [
            "Basic Outfits"
          ]
        },
        "Lost In Midnight/Lost-in-Midnight": {
          "Planets": [
            "Rum Cellar",
            "Vesta"
          ],
          "Outfitters": [
            "Basic Outfits"
          ]
        },
        "POOT/poot-senza-solaria": {
          "Planets": [
            "Daemonium Solaria Station",
            "Delva Solaris Station",
            "Everything ",
            "Poot ",
            "Ragnarok Solaris Station",
            "Senza Solaria",
            "Ursa Polaris Station II",
            "Valkirus Solaris Station"
          ],
          "Outfitters": [
            "Senza Solaria Plugin Outfits",
            "Senza Solaria Unlockall Outfits Plugin"
          ]
        },
        "POOT/endless_sky_senza_solaria": {
          "Planets": [
            "Daemonium Solaria Station",
            "Delva Solaris Station",
            "Everything ",
            "Poot ",
            "Ragnarok Solaris Station",
            "Senza Solaria",
            "Ursa Polaris Station II",
            "Valkirus Solaris Station"
          ],
          "Outfitters": [
            "Senza Solaria Plugin Outfits",
            "Senza Solaria Unlockall Outfits Plugin"
          ]
        },
        "POOT/poot-senza-solaria_senza_solaria": {
          "Planets": [
            "Daemonium Solaria Station",
            "Delva Solaris Station",
            "Everything ",
            "Poot ",
            "Ragnarok Solaris Station",
            "Senza Solaria",
            "Ursa Polaris Station II",
            "Valkirus Solaris Station"
          ],
          "Outfitters": [
            "Senza Solaria Plugin Outfits",
            "Senza Solaria Unlockall Outfits Plugin"
          ]
        }
      },
      "pluginId": "POOT/poot-infinite-expanse"
    },
    {
      "name": "Void Weapon Expansion S",
      "category": "Void Technology",
      "cost": 160000,
      "thumbnail": "outfit/yellow screwdriver",
      "mass": 20,
      "outfit space": -5,
      "weapon capacity": 20,
      "unplunderable": 1,
      "heat generation": 1.5,
      "description": "By utilizing void technology, this expansion increases weapon capacity by 20 at the cost of 5 Outfit Space.",
      "governments": {
        "Lemurias Extra ES Stuff/Lemurias-Extra-ES-Stuff": {
          "Sayari Plushie": true,
          "Anime Organization": true,
          "Republic": true
        },
        "Mega Freight/Mega-Freight": {
          "Republic": true
        },
        "sensor/sensor": {
          "sensor": true
        },
        "POOT/poot-senza-solaria": {
          "Syndicate": true
        },
        "POOT/endless_sky_senza_solaria": {
          "Syndicate": true
        },
        "POOT/poot-senza-solaria_senza_solaria": {
          "Syndicate": true
        }
      },
      "locations": {
        "official-game/endless-sky": {
          "Planets": [
            "Alfheim",
            "Bivrost",
            "Bloodsea",
            "Clark",
            "Crossroads",
            "Dancer",
            "Delve",
            "Freedom",
            "Furnace",
            "Gagarin",
            "Geyser",
            "Greenwater",
            "Haven",
            "Haze",
            "Heartland",
            "Ingot",
            "Jakobsen",
            "Longjump",
            "Mainsail",
            "Maker",
            "Millrace",
            "Mordente-Bridi",
            "New Argentina",
            "New Boston",
            "New Holland",
            "New Tortuga",
            "New Wales",
            "Nifel",
            "Nimbus",
            "Norn",
            "Poseidos",
            "Stormhold",
            "Thrall",
            "Thunder",
            "Trinket",
            "Windblain"
          ],
          "Outfitters": [
            "Basic Outfits"
          ]
        },
        "Zuckungs list/galactic.capital.investment": {
          "Planets": [
            "Sapphire"
          ],
          "Outfitters": [
            "Basic Outfits"
          ]
        },
        "Beccas-Endless-Expansion/Beccas-Endless-Expansion": {
          "Planets": [
            "Haven"
          ],
          "Outfitters": [
            "Basic Outfits"
          ]
        },
        "Galactic War/Galactic-War": {
          "Planets": [
            "Letamos-P382S",
            "Muxkear"
          ],
          "Outfitters": [
            "Basic Outfits"
          ]
        },
        "Lemurias Extra ES Stuff/Lemurias-Extra-ES-Stuff": {
          "Planets": [
            "Barachen",
            "Bardanistra",
            "Denchrao",
            "Eisei",
            "Ekarai",
            "Laateli",
            "Leroo Station",
            "Markaai",
            "Mirdenheim",
            "Ondoristra",
            "Parton",
            "Rodoluki",
            "Sayari Ring",
            "Steirek",
            "Tarsia",
            "Yinachr"
          ],
          "Outfitters": [
            "Basic Outfits"
          ]
        },
        "Mega Freight/Mega-Freight": {
          "Planets": [
            "Ankulah Ship Breaking Station",
            "Vinci"
          ],
          "Outfitters": [
            "Basic Outfits"
          ]
        },
        "sensor/sensor": {
          "Planets": [
            "lidar"
          ],
          "Outfitters": [
            "Basic Outfits"
          ]
        },
        "Lost In Midnight/Lost-in-Midnight": {
          "Planets": [
            "Rum Cellar",
            "Vesta"
          ],
          "Outfitters": [
            "Basic Outfits"
          ]
        },
        "POOT/poot-senza-solaria": {
          "Planets": [
            "Daemonium Solaria Station",
            "Delva Solaris Station",
            "Everything ",
            "Poot ",
            "Ragnarok Solaris Station",
            "Senza Solaria",
            "Ursa Polaris Station II",
            "Valkirus Solaris Station"
          ],
          "Outfitters": [
            "Senza Solaria Plugin Outfits",
            "Senza Solaria Unlockall Outfits Plugin"
          ]
        },
        "POOT/endless_sky_senza_solaria": {
          "Planets": [
            "Daemonium Solaria Station",
            "Delva Solaris Station",
            "Everything ",
            "Poot ",
            "Ragnarok Solaris Station",
            "Senza Solaria",
            "Ursa Polaris Station II",
            "Valkirus Solaris Station"
          ],
          "Outfitters": [
            "Senza Solaria Plugin Outfits",
            "Senza Solaria Unlockall Outfits Plugin"
          ]
        },
        "POOT/poot-senza-solaria_senza_solaria": {
          "Planets": [
            "Daemonium Solaria Station",
            "Delva Solaris Station",
            "Everything ",
            "Poot ",
            "Ragnarok Solaris Station",
            "Senza Solaria",
            "Ursa Polaris Station II",
            "Valkirus Solaris Station"
          ],
          "Outfitters": [
            "Senza Solaria Plugin Outfits",
            "Senza Solaria Unlockall Outfits Plugin"
          ]
        }
      },
      "pluginId": "POOT/poot-infinite-expanse"
    },
    {
      "name": "Void Weapon Expansion XL",
      "category": "Void Technology",
      "cost": 16000000,
      "thumbnail": "outfit/yellow screwdriver",
      "mass": 2000,
      "outfit space": -500,
      "weapon capacity": 2000,
      "heat generation": 150,
      "unplunderable": 1,
      "description": "By utilizing void technology, this expansion increases weapon capacity by 2000 at the cost of 500 Outfit Space.",
      "governments": {
        "Lemurias Extra ES Stuff/Lemurias-Extra-ES-Stuff": {
          "Sayari Plushie": true,
          "Anime Organization": true,
          "Republic": true
        },
        "Mega Freight/Mega-Freight": {
          "Republic": true
        },
        "sensor/sensor": {
          "sensor": true
        },
        "POOT/poot-senza-solaria": {
          "Syndicate": true
        },
        "POOT/endless_sky_senza_solaria": {
          "Syndicate": true
        },
        "POOT/poot-senza-solaria_senza_solaria": {
          "Syndicate": true
        }
      },
      "locations": {
        "official-game/endless-sky": {
          "Planets": [
            "Alfheim",
            "Bivrost",
            "Bloodsea",
            "Clark",
            "Crossroads",
            "Dancer",
            "Delve",
            "Freedom",
            "Furnace",
            "Gagarin",
            "Geyser",
            "Greenwater",
            "Haven",
            "Haze",
            "Heartland",
            "Ingot",
            "Jakobsen",
            "Longjump",
            "Mainsail",
            "Maker",
            "Millrace",
            "Mordente-Bridi",
            "New Argentina",
            "New Boston",
            "New Holland",
            "New Tortuga",
            "New Wales",
            "Nifel",
            "Nimbus",
            "Norn",
            "Poseidos",
            "Stormhold",
            "Thrall",
            "Thunder",
            "Trinket",
            "Windblain"
          ],
          "Outfitters": [
            "Basic Outfits"
          ]
        },
        "Zuckungs list/galactic.capital.investment": {
          "Planets": [
            "Sapphire"
          ],
          "Outfitters": [
            "Basic Outfits"
          ]
        },
        "Beccas-Endless-Expansion/Beccas-Endless-Expansion": {
          "Planets": [
            "Haven"
          ],
          "Outfitters": [
            "Basic Outfits"
          ]
        },
        "Galactic War/Galactic-War": {
          "Planets": [
            "Letamos-P382S",
            "Muxkear"
          ],
          "Outfitters": [
            "Basic Outfits"
          ]
        },
        "Lemurias Extra ES Stuff/Lemurias-Extra-ES-Stuff": {
          "Planets": [
            "Barachen",
            "Bardanistra",
            "Denchrao",
            "Eisei",
            "Ekarai",
            "Laateli",
            "Leroo Station",
            "Markaai",
            "Mirdenheim",
            "Ondoristra",
            "Parton",
            "Rodoluki",
            "Sayari Ring",
            "Steirek",
            "Tarsia",
            "Yinachr"
          ],
          "Outfitters": [
            "Basic Outfits"
          ]
        },
        "Mega Freight/Mega-Freight": {
          "Planets": [
            "Ankulah Ship Breaking Station",
            "Vinci"
          ],
          "Outfitters": [
            "Basic Outfits"
          ]
        },
        "sensor/sensor": {
          "Planets": [
            "lidar"
          ],
          "Outfitters": [
            "Basic Outfits"
          ]
        },
        "Lost In Midnight/Lost-in-Midnight": {
          "Planets": [
            "Rum Cellar",
            "Vesta"
          ],
          "Outfitters": [
            "Basic Outfits"
          ]
        },
        "POOT/poot-senza-solaria": {
          "Planets": [
            "Daemonium Solaria Station",
            "Delva Solaris Station",
            "Everything ",
            "Poot ",
            "Ragnarok Solaris Station",
            "Senza Solaria",
            "Ursa Polaris Station II",
            "Valkirus Solaris Station"
          ],
          "Outfitters": [
            "Senza Solaria Plugin Outfits",
            "Senza Solaria Unlockall Outfits Plugin"
          ]
        },
        "POOT/endless_sky_senza_solaria": {
          "Planets": [
            "Daemonium Solaria Station",
            "Delva Solaris Station",
            "Everything ",
            "Poot ",
            "Ragnarok Solaris Station",
            "Senza Solaria",
            "Ursa Polaris Station II",
            "Valkirus Solaris Station"
          ],
          "Outfitters": [
            "Senza Solaria Plugin Outfits",
            "Senza Solaria Unlockall Outfits Plugin"
          ]
        },
        "POOT/poot-senza-solaria_senza_solaria": {
          "Planets": [
            "Daemonium Solaria Station",
            "Delva Solaris Station",
            "Everything ",
            "Poot ",
            "Ragnarok Solaris Station",
            "Senza Solaria",
            "Ursa Polaris Station II",
            "Valkirus Solaris Station"
          ],
          "Outfitters": [
            "Senza Solaria Plugin Outfits",
            "Senza Solaria Unlockall Outfits Plugin"
          ]
        }
      },
      "pluginId": "POOT/poot-infinite-expanse"
    }
  ],
  "effects": [],
  "parsedAt": "2026-07-01T08:02:29.433Z"
}