[
  {
    "name": "Ion Killer Cannon",
    "category": "Guns",
    "plural": "Energy Blasters",
    "licenses": "Friendly",
    "cost": 50000,
    "thumbnail": "outfit/ion killer cannon",
    "mass": 6,
    "outfit space": -8,
    "weapon capacity": -8,
    "gun ports": -1,
    "weapon": {
      "sprite": "projectile/blaster",
      "sound": "blaster",
      "hit effect": "blaster impact",
      "inaccuracy": 3,
      "velocity": 10.625,
      "lifetime": 48,
      "reload": 14,
      "firing energy": 6.3,
      "firing heat": 12,
      "shield damage": 11,
      "hull damage": 7,
      "ion damage": 1.2
    },
    "description": "Need something to deal with those pesky missile-chucking pirates? Try out our Ion Killer Cannon! Why, all you have to do is get in range for a second, and ion-pump them! \tMade entirely by Fire Corporation.",
    "governments": {
      "Lemurias Extra ES Stuff/Lemurias-Extra-ES-Stuff": {
        "Sayari Plushie": true
      },
      "Mega Freight/Mega-Freight": {
        "Republic": true,
        "MGF: NGK Security": true,
        "Syndicate": true
      },
      "sensor/sensor": {
        "sensor": true
      }
    },
    "locations": {
      "official-game/endless-sky": {
        "Planets": [
          "Buccaneer Bay",
          "Geminus",
          "Greenwater",
          "New Argentina",
          "New Boston",
          "New Britain",
          "New China",
          "New Holland",
          "New Tortuga",
          "New Wales",
          "Smuggler's Den"
        ],
        "Outfitters": [
          "Basic Outfits",
          "Common Outfits"
        ]
      },
      "Zuckungs list/galactic.capital.investment": {
        "Planets": [
          "Sapphire"
        ],
        "Outfitters": [
          "Basic Outfits",
          "Common Outfits"
        ]
      },
      "Lemurias Extra ES Stuff/Lemurias-Extra-ES-Stuff": {
        "Planets": [
          "Leroo Station",
          "Ondoristra",
          "Salistra",
          "Sayari Ring",
          "Steirek"
        ],
        "Outfitters": [
          "Basic Outfits",
          "Basic Weapons",
          "Common Outfits"
        ]
      },
      "Mega Freight/Mega-Freight": {
        "Planets": [
          "Ankaim Orbital Station",
          "Ankulah Ship Breaking Station",
          "CSSY-06 Ningxi Station",
          "Canaveral Naval Yard",
          "GS1 Galaxy Station",
          "Nordlin Navy Yard",
          "OAS4001 Wilkes Station",
          "Ourea Naval Arsenal",
          "SBO1 Zagreus Station",
          "Vinci",
          "Yokosuka Naval Arsenal"
        ],
        "Outfitters": [
          "Basic Outfits",
          "Common Outfits"
        ]
      },
      "Lost In Midnight/Lost-in-Midnight": {
        "Planets": [
          "Rum Cellar",
          "Smuggler's Den",
          "Wang Xiang Tai"
        ],
        "Outfitters": [
          "Basic Outfits",
          "Common Outfits"
        ]
      },
      "sensor/sensor": {
        "Planets": [
          "lidar"
        ],
        "Outfitters": [
          "Basic Outfits",
          "Basic Weapons"
        ]
      }
    },
    "pluginId": "Fire Corporation/Fire-Corporation"
  },
  {
    "name": "Particle Sniper",
    "category": "Guns",
    "plural": "Particle Cannons",
    "licenses": "Friendly",
    "cost": 280000,
    "thumbnail": "outfit/particle sniper",
    "mass": 32,
    "outfit space": -32,
    "weapon capacity": -32,
    "gun ports": -1,
    "weapon": {
      "sprite": "projectile/particle beam",
      "sound": "particle",
      "hit effect": "particle impact",
      "inaccuracy": 0.5,
      "velocity": 38,
      "lifetime": 25,
      "reload": 20,
      "firing energy": 38,
      "firing force": 10,
      "firing heat": 125,
      "shield damage": 67,
      "hull damage": 64,
      "hit force": 80
    },
    "description": "What is the most popular feature of the Particle Cannon? It's long range! Well, this gun makes that range better! \tMade entirely by Fire Corporation.",
    "governments": {
      "Lemurias Extra ES Stuff/Lemurias-Extra-ES-Stuff": {
        "Sayari Plushie": true,
        "Pirate": true
      },
      "Mega Freight/Mega-Freight": {
        "Republic": true,
        "MGF: NGK Security": true,
        "Syndicate": true
      },
      "sensor/sensor": {
        "sensor": true
      },
      "Fire Corporation/Fire-Corporation": {
        "Fire Corporation (Hunters)": true,
        "Bounty (FC)": true,
        "Fire Corporation": true
      }
    },
    "locations": {
      "official-game/endless-sky": {
        "Planets": [
          "Buccaneer Bay",
          "Geminus",
          "Greenwater",
          "New Argentina",
          "New Boston",
          "New Britain",
          "New China",
          "New Holland",
          "New Tortuga",
          "New Wales",
          "Smuggler's Den"
        ],
        "Outfitters": [
          "Basic Outfits",
          "Common Outfits"
        ],
        "ShipyardPlanets": [
          "Geminus",
          "Greenwater",
          "New Boston",
          "New Britain",
          "New Tortuga"
        ],
        "Systems": [
          "Acrux",
          "Adhara",
          "Albaldah",
          "Albireo",
          "Aldebaran",
          "Aldhibain",
          "Algieba",
          "Alheka",
          "Alhena",
          "Alnasl",
          "Alniyat",
          "Alpha Arae",
          "Alpha Centauri",
          "Alphard",
          "Altair",
          "Aludra",
          "Antares",
          "Aspidiske",
          "Avior",
          "Beta Lupi",
          "Betelgeuse",
          "Canopus",
          "Capella",
          "Cardax",
          "Castor",
          "Denebola",
          "Dschubba",
          "Dubhe",
          "Eber",
          "Elnath",
          "Epsilon Leonis",
          "Eteron",
          "Fala",
          "Gamma Corvi",
          "Gomeisa",
          "Hadar",
          "Han",
          "Ildaria",
          "Izar",
          "Kornephoros",
          "Kraz",
          "Kursa",
          "Markeb",
          "Mebsuta",
          "Menkalinan",
          "Merak",
          "Miaplacidus",
          "Mimosa",
          "Minkar",
          "Mirzam",
          "Naos",
          "Nihal",
          "Phact",
          "Phecda",
          "Pherkad",
          "Phurad",
          "Pollux",
          "Porrima",
          "Procyon",
          "Regor",
          "Rigel",
          "Sabik",
          "Saiph",
          "Sargas",
          "Shaula",
          "Sirius",
          "Sol",
          "Sospi",
          "Spica",
          "Suhail",
          "Talita",
          "Tania Australis",
          "Tejat",
          "Unukalhai",
          "Vega",
          "Volax",
          "Wazn",
          "Wei",
          "Wezen",
          "Yed Prior",
          "Zeta Centauri",
          "Zosma",
          "Zubenelgenubi",
          "Zubeneschamali"
        ]
      },
      "Zuckungs list/galactic.capital.investment": {
        "Planets": [
          "Sapphire"
        ],
        "Outfitters": [
          "Basic Outfits",
          "Common Outfits"
        ],
        "ShipyardPlanets": [
          "Sapphire"
        ]
      },
      "Lemurias Extra ES Stuff/Lemurias-Extra-ES-Stuff": {
        "Planets": [
          "Leroo Station",
          "Ondoristra",
          "Salistra",
          "Sayari Ring",
          "Steirek"
        ],
        "Outfitters": [
          "Basic Outfits",
          "Basic Weapons",
          "Common Outfits"
        ],
        "ShipyardPlanets": [
          "Kestrix II"
        ],
        "Systems": [
          "94 Merisai",
          "Airuka",
          "Aixafer",
          "Aljuik",
          "Alkxaai",
          "Arau",
          "Arket",
          "Corua",
          "Darceas",
          "Daxter",
          "Denleitt",
          "Deriato",
          "Deriie",
          "Finduue",
          "Gensokyo",
          "Illumina",
          "Illuria",
          "Jalak",
          "Jarkiiens",
          "Karita",
          "Kolicasa",
          "Lakodelfraddi",
          "Lesarkei",
          "Lesokicasa",
          "Littike",
          "Mersat",
          "Nardacus",
          "Oldothe",
          "Onuka",
          "Paricasa",
          "Pelitol",
          "Poreu",
          "Porsuei",
          "Posteli",
          "Raidei",
          "Sedlai",
          "Sprooe",
          "Suerolii",
          "Telicasa",
          "Vachrau",
          "Varisa",
          "Vefrua",
          "Vensur",
          "Zarkxaa"
        ]
      },
      "Mega Freight/Mega-Freight": {
        "Planets": [
          "Ankaim Orbital Station",
          "Ankulah Ship Breaking Station",
          "CSSY-06 Ningxi Station",
          "Canaveral Naval Yard",
          "GS1 Galaxy Station",
          "Nordlin Navy Yard",
          "OAS4001 Wilkes Station",
          "Ourea Naval Arsenal",
          "SBO1 Zagreus Station",
          "Vinci",
          "Yokosuka Naval Arsenal"
        ],
        "Outfitters": [
          "Basic Outfits",
          "Common Outfits"
        ],
        "ShipyardPlanets": [
          "Ankulah Ship Breaking Station",
          "Canaveral Naval Yard",
          "GS1 Galaxy Station",
          "Nordlin Navy Yard",
          "Ourea Naval Arsenal",
          "SBO1 Zagreus Station",
          "Yokosuka Naval Arsenal"
        ]
      },
      "Lost In Midnight/Lost-in-Midnight": {
        "Planets": [
          "Rum Cellar",
          "Smuggler's Den",
          "Wang Xiang Tai"
        ],
        "Outfitters": [
          "Basic Outfits",
          "Common Outfits"
        ]
      },
      "sensor/sensor": {
        "Planets": [
          "lidar"
        ],
        "Outfitters": [
          "Basic Outfits",
          "Basic Weapons"
        ],
        "ShipyardPlanets": [
          "lidar"
        ]
      },
      "Fire Corporation/Fire-Corporation": {
        "Ships": [
          "Fire Assassin"
        ]
      }
    },
    "pluginId": "Fire Corporation/Fire-Corporation"
  },
  {
    "name": "Friendly License",
    "category": "Licenses",
    "thumbnail": "outfit/license",
    "description": "This checks if you are a pirate or not to see if you can buy Fire Corporation ships and outfits.",
    "governments": {
      "Fire-Corporation": {
        "Fire-Corporation": true
      }
    },
    "locations": {
      "Fire Corporation/Fire-Corporation": {
        "_deprecated/unused": true
      }
    },
    "pluginId": "Fire Corporation/Fire-Corporation"
  }
]